iobrpy/__init__.py
iobrpy/main.py
iobrpy/SpecHLA/SpecHLA.py
iobrpy/SpecHLA/__init__.py
iobrpy/SpecHLA/extract_hla_read.py
iobrpy/SpecHLA/index.sh
iobrpy/SpecHLA/install_spechap.sh
iobrpy/SpecHLA/bin/bcftools
iobrpy/SpecHLA/bin/blast2sam.pl
iobrpy/SpecHLA/bin/blastn
iobrpy/SpecHLA/bin/libwfa2.so.0
iobrpy/SpecHLA/bin/SpecHap/CMakeLists.txt
iobrpy/SpecHLA/bin/SpecHap/LICENSE.md
iobrpy/SpecHLA/bin/SpecHap/README.md
iobrpy/SpecHLA/bin/SpecHap/frag_io.cpp
iobrpy/SpecHLA/bin/SpecHap/frag_io.h
iobrpy/SpecHLA/bin/SpecHap/graph.cpp
iobrpy/SpecHLA/bin/SpecHap/graph.h
iobrpy/SpecHLA/bin/SpecHap/hic_util.cpp
iobrpy/SpecHLA/bin/SpecHap/hic_util.h
iobrpy/SpecHLA/bin/SpecHap/indexing.h
iobrpy/SpecHLA/bin/SpecHap/main.cpp
iobrpy/SpecHLA/bin/SpecHap/optionparser.h
iobrpy/SpecHLA/bin/SpecHap/phaser.cpp
iobrpy/SpecHLA/bin/SpecHap/phaser.h
iobrpy/SpecHLA/bin/SpecHap/results.cpp
iobrpy/SpecHLA/bin/SpecHap/results.h
iobrpy/SpecHLA/bin/SpecHap/spectral.cpp
iobrpy/SpecHLA/bin/SpecHap/spectral.h
iobrpy/SpecHLA/bin/SpecHap/tenx_util.cpp
iobrpy/SpecHLA/bin/SpecHap/tenx_util.h
iobrpy/SpecHLA/bin/SpecHap/type.cpp
iobrpy/SpecHLA/bin/SpecHap/type.h
iobrpy/SpecHLA/bin/SpecHap/util.cpp
iobrpy/SpecHLA/bin/SpecHap/util.h
iobrpy/SpecHLA/bin/SpecHap/vcf_io.cpp
iobrpy/SpecHLA/bin/SpecHap/vcf_io.h
iobrpy/SpecHLA/bin/SpecHap/Eigen/CMakeLists.txt
iobrpy/SpecHLA/bin/SpecHap/Eigen/Cholesky
iobrpy/SpecHLA/bin/SpecHap/Eigen/CholmodSupport
iobrpy/SpecHLA/bin/SpecHap/Eigen/Core
iobrpy/SpecHLA/bin/SpecHap/Eigen/Dense
iobrpy/SpecHLA/bin/SpecHap/Eigen/Eigen
iobrpy/SpecHLA/bin/SpecHap/Eigen/Eigenvalues
iobrpy/SpecHLA/bin/SpecHap/Eigen/Geometry
iobrpy/SpecHLA/bin/SpecHap/Eigen/Householder
iobrpy/SpecHLA/bin/SpecHap/Eigen/IterativeLinearSolvers
iobrpy/SpecHLA/bin/SpecHap/Eigen/Jacobi
iobrpy/SpecHLA/bin/SpecHap/Eigen/LU
iobrpy/SpecHLA/bin/SpecHap/Eigen/MetisSupport
iobrpy/SpecHLA/bin/SpecHap/Eigen/OrderingMethods
iobrpy/SpecHLA/bin/SpecHap/Eigen/PaStiXSupport
iobrpy/SpecHLA/bin/SpecHap/Eigen/PardisoSupport
iobrpy-0.1.7.dist-info/licenses/LICENSE
iobrpy-0.1.7.dist-info/METADATA
iobrpy-0.1.7.dist-info/WHEEL
iobrpy-0.1.7.dist-info/entry_points.txt
iobrpy-0.1.7.dist-info/top_level.txt
iobrpy-0.1.7.dist-info/RECORD
