Metadata-Version: 2.4
Name: iobrpy
Version: 0.1.7
Summary: Immuno-Oncology Biological Research tools in Python
Author-email: Haonan Huang <2905611068@qq.com>, Dongqiang Zeng <interlaken@smu.edu.cn>
License: MIT License
Project-URL: Homepage, https://github.com/IOBR/IOBRpy
Project-URL: Issues, https://github.com/IOBR/IOBRpy/issues
Keywords: bioinformatics,immuno-oncology,RNA-seq,deconvolution
Classifier: Intended Audience :: Science/Research
Classifier: Topic :: Scientific/Engineering :: Bio-Informatics
Classifier: License :: OSI Approved :: MIT License
Classifier: Programming Language :: Python :: 3
Classifier: Programming Language :: Python :: 3 :: Only
Classifier: Operating System :: OS Independent
Requires-Python: >=3.9
License-File: LICENSE
Requires-Dist: numpy>=1.22
Requires-Dist: pandas>=1.5
Requires-Dist: scipy>=1.9
Requires-Dist: scikit-learn>=1.2
Requires-Dist: statsmodels>=0.13
Requires-Dist: matplotlib>=3.7
Requires-Dist: tqdm>=4.66
Requires-Dist: gseapy>=1.0.6
Requires-Dist: joblib>=1.3
Requires-Dist: multiqc==1.31
Requires-Dist: xarray>=0.20
Dynamic: license-file
